{"cameraMode":{"drawMode":0,"name":"Shaded","section":"Shading Mode"},"sceneLighting":true,"audioPlay":false,"sceneViewState":{"showFog":true,"showMaterialUpdate":false,"showSkybox":true,"showFlares":true,"showImageEffects":true,"showParticleSystems":true},"in2DMode":false,"pivot":{"x":1.043809413909912,"y":2.401837110519409,"z":-7.962634086608887},"rotation":{"x":0.004274351987987757,"y":0.9427077174186707,"z":-0.012090112082660199,"w":0.3333733081817627},"size":5.1151628494262699,"orthographic":false}